mynn/__init__.py
mynn/_version.py
mynn/activations/__init__.py
mynn/initializers/__init__.py
mynn/layers/__init__.py
mynn/layers/batchnorm.py
mynn/layers/conv.py
mynn/layers/dense.py
mynn/layers/dropout.py
mynn/layers/prelu.py
mynn/losses/__init__.py
mynn/losses/cross_entropy.py
mynn/losses/focal_loss.py
mynn/losses/huber_loss.py
mynn/losses/kl_divergence.py
mynn/losses/l1_loss.py
mynn/losses/mean_squared_loss.py
mynn/losses/negative_log_likelihood.py
mynn/optimizers/__init__.py
mynn/optimizers/adadelta.py
mynn/optimizers/adagrad.py
mynn/optimizers/adam.py
mynn/optimizers/adamax.py
mynn/optimizers/rmsprop.py
mynn/optimizers/sgd.py
tests/__init__.py
tests/integration.py
tests/test_losses.py
mynn-0.9.4.dist-info/LICENSE
mynn-0.9.4.dist-info/METADATA
mynn-0.9.4.dist-info/WHEEL
mynn-0.9.4.dist-info/top_level.txt
mynn-0.9.4.dist-info/RECORD
