Metadata-Version: 2.1
Name: mynn
Version: 0.9.4
Summary: A pure-Python neural network library
Home-page: https://github.com/davidmascharka/MyNN
Author: David Mascharka
License: MIT
Platform: UNKNOWN
Classifier: Development Status :: 4 - Beta
Classifier: License :: OSI Approved :: MIT License
Classifier: Operating System :: OS Independent
Classifier: Intended Audience :: Science/Research
Classifier: Intended Audience :: Education
Classifier: Programming Language :: Python
Classifier: Programming Language :: Python :: 3
Classifier: Programming Language :: Python :: 3.6
Classifier: Programming Language :: Python :: 3.7
Classifier: Topic :: Scientific/Engineering
Requires-Python: >=3.6
License-File: LICENSE
Requires-Dist: numpy (>=1.13)
Requires-Dist: mygrad (>=1.6)
